evprim/__init__.py
evprim/composite.py
evprim/even.py
evprim/prime.py
evprim-0.2.dist-info/LICENSE.txt
evprim-0.2.dist-info/METADATA
evprim-0.2.dist-info/WHEEL
evprim-0.2.dist-info/top_level.txt
evprim-0.2.dist-info/RECORD
