Metadata-Version: 2.1
Name: evprim
Version: 0.2
Summary: This library has the object of identify even, odd and compound numbers as individually or in tuple/lists.
Home-page: https://github.com/moises4729/evprim
Author: Moises Marin
Author-email: moisesedumh@gmail.com
License: UNKNOWN
Platform: UNKNOWN
Classifier: Programming Language :: Python :: 3
Classifier: License :: OSI Approved :: MIT License
Classifier: Operating System :: OS Independent
